pymodd-1.1.0.dist-info/METADATA
pymodd-1.1.0.dist-info/WHEEL
pymodd-1.1.0.dist-info/entry_points.txt
pymodd-1.1.0.dist-info/licenses/LICENSE.txt
pymodd/__init__.py
pymodd/_pymodd_helper.cpython-313-darwin.so
pymodd/_pymodd_helper.pyi
pymodd/actions.py
pymodd/console_scripts/pymodd_command.py
pymodd/core/base.py
pymodd/core/file.py
pymodd/core/folder.py
pymodd/core/function.py
pymodd/core/script.py
pymodd/entity_script.py
pymodd/function/group.py
pymodd/function/selected_entity.py
pymodd/function/type.py
pymodd/functions.py
pymodd/game.py
pymodd/py.typed
pymodd/script.py
pymodd/todo.txt
pymodd/utils/Default Game.json
pymodd/utils/generate_random_key.py
pymodd/utils/to_dict.py
pymodd/utils/type_of_item.py
pymodd/variable/data_type.py
pymodd/variable/variable_iterator.py
pymodd/variable/variable_type.py
pymodd/variable_types.py
pymodd-1.1.0.dist-info/RECORD
