Metadata-Version: 2.4
Name: pymodd
Version: 1.1.0
Classifier: Programming Language :: Rust
Classifier: Programming Language :: Python :: Implementation :: CPython
Classifier: Programming Language :: Python :: Implementation :: PyPy
Requires-Dist: case-converter==1.1.0
License-File: LICENSE.txt
Summary: create and edit modd.io games in python
Author: Jeff
License: MIT
Requires-Python: >=3.8
Project-URL: repository, https://github.com/jeff5343/pymodd
Project-URL: changelog, https://github.com/jeff5343/pymodd/releases
